{"api-examples.md":"DE8oo2S2","components_alert.md":"CeGW0MsB","components_button.md":"DKnxrOsV","components_collapse.md":"BWvm7Ff7","components_dropdown.md":"D5PvUe2B","components_form.md":"CjnRCR4z","components_input.md":"BrqIps4E","components_message.md":"BrkQUQgX","components_notification.md":"BCTdOCeo","components_popconfirm.md":"BEsVp8rG","components_select.md":"D6IYFmBd","components_switch.md":"DPVHz3dc","components_tooltip.md":"BI5JCwjh","get-started.md":"DNZtRAbM","index.md":"DsSPCqtb"}
